freedns/__init__.py
freedns/client.py
freedns_client-0.1.3.dist-info/LICENSE
freedns_client-0.1.3.dist-info/METADATA
freedns_client-0.1.3.dist-info/WHEEL
freedns_client-0.1.3.dist-info/top_level.txt
freedns_client-0.1.3.dist-info/RECORD
