Metadata-Version: 2.1
Name: freedns-client
Version: 0.1.3
Summary: A Python package for interacting with FreeDNS.afraid.org
Home-page: https://github.com/ading2210/freedns-client
Author: ading2210
License: GPLv3
Classifier: Programming Language :: Python :: 3
Classifier: License :: OSI Approved :: GNU General Public License (GPL)
Classifier: Operating System :: OS Independent
Requires-Python: >=3.7
License-File: LICENSE
Requires-Dist: cssselect
Requires-Dist: lxml
Requires-Dist: requests
